README.txt
license.txt
setup.py
GrabzIt/AES.py
GrabzIt/BlockFeeder.py
GrabzIt/GrabzItAnimationOptions.py
GrabzIt/GrabzItBaseOptions.py
GrabzIt/GrabzItClient.py
GrabzIt/GrabzItCookie.py
GrabzIt/GrabzItDOCXOptions.py
GrabzIt/GrabzItException.py
GrabzIt/GrabzItHTMLOptions.py
GrabzIt/GrabzItImageOptions.py
GrabzIt/GrabzItPDFOptions.py
GrabzIt/GrabzItTableOptions.py
GrabzIt/GrabzItVideoOptions.py
GrabzIt/GrabzItWaterMark.py
GrabzIt/Request.py
GrabzIt/ScreenShotStatus.py
GrabzIt/Util.py
GrabzIt/__init__.py
GrabzIt.egg-info/PKG-INFO
GrabzIt.egg-info/SOURCES.txt
GrabzIt.egg-info/dependency_links.txt
GrabzIt.egg-info/top_level.txt
tests/TestGrabzItClient.py