Metadata-Version: 2.4
Name: GrabzIt
Version: 3.5.7.1
Summary: GrabzIt enables allows you to programmatically convert web pages and HTML into images, DOCX, videos, rendered HTML, PDFs, CSVs and spreadsheets. Additionally GrabzIt allows you to convert online videos into animated GIFs
Home-page: https://grabz.it/api/python/
Author: GrabzIt
Author-email: support@grabz.it
License: MIT Licence
License-File: license.txt
Dynamic: author
Dynamic: author-email
Dynamic: description
Dynamic: description-content-type
Dynamic: home-page
Dynamic: license
Dynamic: license-file
Dynamic: summary
